setup.py
distributions_esra/Binomialdistribution.py
distributions_esra/Gaussiandistribution.py
distributions_esra/Generaldistribution.py
distributions_esra/__init__.py
distributions_esra.egg-info/PKG-INFO
distributions_esra.egg-info/SOURCES.txt
distributions_esra.egg-info/dependency_links.txt
distributions_esra.egg-info/not-zip-safe
distributions_esra.egg-info/top_level.txt