Metadata-Version: 1.0
Name: distributions-esra
Version: 2.1
Summary: Gaussian distributions
Home-page: UNKNOWN
Author: esra ai
Author-email: esra.al@gmail.com
License: UNKNOWN
Platform: UNKNOWN
